BIS_CBPR/BIS.py
BIS_CBPR/__init__.py
BIS_CBPR-0.1.0.dist-info/METADATA
BIS_CBPR-0.1.0.dist-info/WHEEL
BIS_CBPR-0.1.0.dist-info/top_level.txt
BIS_CBPR-0.1.0.dist-info/RECORD
